{
  "ok": false,
  "run_id": "20251229-214636-ceed2f",
  "source_type": "chrome",
  "status": "no_items",
  "message": "Canonical invoice validation failed",
  "canonical": null,
  "extracted": {
    "items": [],
    "tableHtml": [],
    "raw_text_length": 56,
    "raw_text_preview": "OWENS CORNING 1901 49TH AVE N MINNEAPOLIS, MN 55430-3793",
    "meta": {
      "source_ref": null
    }
  },
  "validation": {
    "attempted": true,
    "ok": false,
    "errors": [
      {
        "instancePath": "/line_items",
        "schemaPath": "#/properties/line_items/minItems",
        "keyword": "minItems",
        "params": {
          "limit": 1
        },
        "message": "must NOT have fewer than 1 items"
      }
    ]
  },
  "legacy": null,
  "debug": {
    "version": "v2025-12-18cintas-parser-1",
    "source_ref": null,
    "extractedItemsCount": 0,
    "canonicalLineItemsCount": 0,
    "autoLeads": {
      "attempted": true,
      "ok": true,
      "source": "web_scraper",
      "leadCount": 3,
      "cacheKey": "owens corning|55430",
      "inferredZip": "55430"
    }
  },
  "error": null,
  "canonical_preview": {
    "schema_version": "invoice.v1",
    "doc": {
      "doc_id": "DOC-bf90a1ea8620",
      "doc_type": "invoice",
      "invoice_number": null,
      "purchase_order": null,
      "issued_at": "2025-12-30T02:47:03.920Z",
      "service_period": null,
      "currency": "USD",
      "raw_text_hash": "bf90a1ea8620193bb807d4a66def1c66794e507191ab4cc30ae10e06392d9a19",
      "tags": []
    },
    "parties": {
      "vendor": {
        "name": "Unknown Vendor",
        "normalized_name": "unknown vendor",
        "addresses": []
      },
      "customer": {
        "name": "Owens Corning",
        "normalized_name": "owens corning",
        "addresses": [
          {
            "raw": "OWENS CORNING, MINNEAPOLIS, MN 55430-3793",
            "street": "OWENS CORNING",
            "city": "MINNEAPOLIS",
            "state": "MN",
            "postal": "55430",
            "country": "US",
            "confidence": 0.85
          }
        ]
      },
      "bill_to": null,
      "ship_to": {
        "name": "Owens Corning",
        "normalized_name": "owens corning",
        "addresses": [
          {
            "raw": "OWENS CORNING, MINNEAPOLIS, MN 55430-3793",
            "street": "OWENS CORNING",
            "city": "MINNEAPOLIS",
            "state": "MN",
            "postal": "55430",
            "country": "US",
            "confidence": 0.85
          }
        ]
      }
    },
    "line_items": [],
    "totals": {
      "invoice_total": null,
      "weekly_equivalent_total": null,
      "notes": []
    },
    "signals": [],
    "opportunities": [],
    "provenance": {
      "source_type": "chrome",
      "captured_at": "2025-12-30T02:47:03.921Z",
      "parser": {
        "name": "ingest.chrome",
        "version": "1.0.0",
        "warnings": [
          "No line items found in payload (checked multiple candidate keys)."
        ]
      },
      "source_ref": {
        "kind": "unknown",
        "value": null,
        "mime_type": null
      }
    },
    "confidence": {
      "overall": 0.6,
      "fields": [
        {
          "path": "parties.customer.name",
          "score": 0.3,
          "method": "unknown",
          "evidence": []
        },
        {
          "path": "line_items",
          "score": 0.1,
          "method": "parsed",
          "evidence": []
        }
      ]
    }
  }
}